hgsig/__init__.py
hgsig/hgsig.py
hgsig/plots.py
hgsig/utils.py
hgsig-0.1.6.dist-info/LICENSE
hgsig-0.1.6.dist-info/WHEEL
hgsig-0.1.6.dist-info/METADATA
hgsig-0.1.6.dist-info/RECORD
