Metadata-Version: 2.1
Name: hgsig
Version: 0.1.6
Summary: Differential Representation with Hypergeometric Tests
Author-email: Noam Teyssier <noam.teyssier@ucsf.edu>
Classifier: License :: OSI Approved :: MIT License
Requires-Dist: numpy
Requires-Dist: pandas
Requires-Dist: scipy
Requires-Dist: matplotlib
Requires-Dist: seaborn
Requires-Dist: fastcluster
Requires-Dist: tqdm
Requires-Dist: pytest
Requires-Dist: sphinx
Requires-Dist: numpydoc
Requires-Dist: pydata-sphinx-theme
Requires-Dist: sphinx-autodoc-typehints
Project-URL: Home, https://github.com/noamteyssier/hgsig
